rocketpy/Environment.py
rocketpy/Flight.py
rocketpy/Function.py
rocketpy/Rocket.py
rocketpy/SolidMotor.py
rocketpy/__init__.py
rocketpy/__main__.py
rocketpyalpha-0.9.7.dist-info/LICENSE
rocketpyalpha-0.9.7.dist-info/METADATA
rocketpyalpha-0.9.7.dist-info/WHEEL
rocketpyalpha-0.9.7.dist-info/top_level.txt
rocketpyalpha-0.9.7.dist-info/RECORD
