Metadata-Version: 2.1
Name: rocketpyalpha
Version: 0.9.7
Summary: Advanced 6-DOF trajectory simulation for High-Power Rocketry.
Home-page: https://github.com/giovaniceotto/RocketPy
Author: Giovani Hidalgo Ceotto
Author-email: ghceotto@gmail.com
License: UNKNOWN
Platform: UNKNOWN
Classifier: Programming Language :: Python :: 3
Classifier: License :: OSI Approved :: MIT License
Classifier: Operating System :: OS Independent
Requires-Python: >=3.6
